{
  "obsidian-prism-theme@@pt-icons-accent": true,
  "obsidian-prism-theme@@color-schemes-dt": "pt-color-scheme-raven-dt",
  "obsidian-prism-theme@@color-scheme-style-dt": "pt-color-scheme-style-two-tone-and-border-dt",
  "obsidian-prism-theme@@dark-accent-color-preset": "pt-accent-color-cyan-dt",
  "encore-settings@@theme-light": "encore-theme-light-sterling",
  "encore-settings@@theme-dark": "encore-theme-dark-mercury",
  "encore-settings@@colors": "encore-colors-colorful",
  "encore-settings@@encore-disable-grain": false,
  "encore-settings@@encore-fancy-headers": true,
  "encore-settings@@encore-translucency": false,
  "encore-settings@@encore-translucency-background": "encore-bg-frosty"
}